Workbook

Sheet Presupuesto Integrado - Proyect
A1: === PAGINA 1: RECURSOS HUMANOS Y TARIFAS === -> #ERROR!
A2: Rol | B2: Integrante | C2: Salario Referencial (Mes) | D2: Horas Laborables (Mes) | E2: Tarifa por Hora (RH)
A3: Scrum Master | B3: Josué | C3: 750 | D3: 48 | E3: =C3/D3 -> 15.625
A4: Ing. de Requisitos | B4: Mateo | C4: 600 | D4: 48 | E4: =C4/D4 -> 12.5
A5: Ing. de Requisitos | B5: Damián | C5: 600 | D5: 48 | E5: =C5/D5 -> 12.5
A7: === PAGINA 2: MATERIALES Y GASTOS OPERATIVOS === -> #ERROR!
A8: Concepto | B8: Valor Referencial (Mes) | C8: Horas Laborables (Mes) | D8: Costo por Hora
A9: Depreciación Equipos (Promedio) | B9: 27.36 | C9: 48 | D9: =B10/C10 -> 0.39
A10: Servicios Básicos (Luz, Agua, Internet) | B10: 18.72 | C10: 48 | D10: =B11/C11 -> #DIV/0!
A12: === PAGINA 3: ESTIMACION DE COSTOS(FASES 1 Y 2) === -> #ERROR!
A13: Fase | B13: Tarea / Entregable | C13: Responsable | D13: Horas | E13: Costo RH | F13: Costo Material | G13: Gastos Operativos | H13: Costo Total
A14: Fase 1 | B14: Entrevista con el Gerente General | C14: Damián / Josué | D14: 2 | E14: =D16*($E$3+$E$5)/2 -> 28.125 | F14: =D16*$D$10 -> #DIV/0! | G14: =D16*$D$11 -> 0 | H14: =SUM(E16:G16) -> #DIV/0!
A15: Fase 1 | B15: Entrevista con el recepcionista | C15: Damián | D15: 1 | E15: =D17*$E$5 -> 62.5 | F15: =D17*$D$10 -> #DIV/0! | G15: =D17*$D$11 -> 0 | H15: =SUM(E17:G17) -> #DIV/0!
A16: Fase 1 | B16: Entrevista con el entrenador | C16: Damián | D16: 2 | E16: =D18*$E$5 -> 50 | F16: =D18*$D$10 -> #DIV/0! | G16: =D18*$D$11 -> 0 | H16: =SUM(E18:G18) -> #DIV/0!
A17: Fase 1 | B17: Documentación: Minuta Acta N° 001 | C17: Equipo | D17: 5 | E17: =D19*AVERAGE($E$3:$E$5) -> 40.625 | F17: =D19*$D$10 -> #DIV/0! | G17: =D19*$D$11 -> 0 | H17: =SUM(E19:G19) -> #DIV/0!
A18: Fase 1 | B18: Diseño y aplicación de Encuesta | C18: Equipo | D18: 4 | E18: =D20*AVERAGE($E$3:$E$5) -> 54.166667 | F18: =D20*$D$10 -> #DIV/0! | G18: =D20*$D$11 -> 0 | H18: =SUM(E20:G20) -> #DIV/0!
A19: Fase 1 | B19: Documentación: Informe de Encuesta | C19: Mateo | D19: 3 | E19: =D21*$E$4 -> 50 | F19: =D21*$D$10 -> #DIV/0! | G19: =D21*$D$11 -> 0 | H19: =SUM(E21:G21) -> #DIV/0!
A20: Fase 2 | B20: Definición del Problema (Árbol) | C20: Josué | D20: 4 | E20: =D22*$E$3 -> 46.875 | F20: =D22*$D$10 -> #DIV/0! | G20: =D22*$D$11 -> 0 | H20: =SUM(E22:G22) -> #DIV/0!
A21: Fase 2 | B21: Modelo de Negocio Canvas (Actual) | C21: Josué / Mateo | D21: 4 | E21: =D23*($E$3+$E$4)/2 -> 126.5625 | F21: =D23*$D$10 -> #DIV/0! | G21: =D23*$D$11 -> 0 | H21: =SUM(E23:G23) -> #DIV/0!
A22: Fase 2 | B22: Modelo de Negocio Canvas (Mejorado) | C22: Mateo / Damián | D22: 3 | E22: =D24*($E$4+$E$5)/2 -> 62.5 | F22: =D24*$D$10 -> #DIV/0! | G22: =D24*$D$11 -> 0 | H22: =SUM(E24:G24) -> #DIV/0!
A23: Fase 2 | B23: Solución 1 - Nivel 0 | C23: Equipo | D23: 9 | E23: =D25*AVERAGE($E$3:$E$5) -> 108.33333 | F23: =D25*$D$10 -> #DIV/0! | G23: =D25*$D$11 -> 0 | H23: =SUM(E25:G25) -> #DIV/0!
A24: Fase 2 | B24: Solución 1 - Nivel 1 | C24: Equipo | D24: 5 | E24: =D26*AVERAGE($E$3:$E$5) -> 162.5 | F24: =D26*$D$10 -> #DIV/0! | G24: =D26*$D$11 -> 0 | H24: =SUM(E26:G26) -> #DIV/0!
A25: Fase 2 | B25: Solución 2 - Nivel 0 | C25: Mateo / Damián | D25: 8 | E25: =D27*($E$4+$E$5)/2 -> 0 | F25: =D27*$D$10 -> #DIV/0! | G25: =D27*$D$11 -> 0 | H25: =SUM(E27:G27) -> 0
A26: Fase 2 | B26: Solución final - Integración | C26: Equipo | D26: 12 | E26: =D28*AVERAGE($E$3:$E$5) -> 0 | F26: =D28*$D$10 -> #DIV/0! | G26: =D28*$D$11 -> 0 | H26: =SUM(E28:G28) -> 0
A28: === PAGINA 4: RESUMEN DEL PROYECTO === -> #ERROR!
A29: Concepto | B29: Monto
A30: Fase 1: Elicitación de Requisitos | B30: =SUM(H16:H21) -> #DIV/0!
A31: Fase 2: Análisis y Soluciones | B31: =SUM(H22:H28) -> #DIV/0!
A32: Presupuesto para Contingencias (10%) | B32: =(B32+B33)*0.1 -> #REF!
A33: TOTAL DEL PROYECTO | B33: =SUM(B32:B34) -> #REF!

Sheet Recursos Humanos
A1: Rol | B1: Integrante | C1: Salario Mensual | D1: Horas Mes | E1: Tarifa por Hora (TH) | F1: Tarifa por Hora Extra (THE) | G1: Tarifa Promedio Ponderada
A2: Scrum Master | B2: Josué | C2: 750 | D2: 60 | E2: =IFERROR(C2/D2, 0) -> 12.5 | F2: =E2*1.5 -> 18.75 | G2: =(E2*6 + E2*1.5*6 + E2*2*3) / 15 -> 17.5
A3: Ingeniero de Requisitos | B3: Mateo | C3: 600 | D3: 60 | E3: =IFERROR(C3/D3, 0) -> 10 | F3: =E3*1.5 -> 15 | G3: =(E3*6 + E3*1.5*6 + E3*2*3) / 15 -> 14
A4: Ingeniero de Requisitos | B4: Damián | C4: 600 | D4: 60 | E4: =IFERROR(C4/D4, 0) -> 10 | F4: =E4*1.5 -> 15 | G4: =(E4*6 + E4*1.5*6 + E4*2*3) / 15 -> 14
A6: Trabajo por Día
A7: Rol | B7: Integrante | C7: Horas Normales (L,M,V) | D7: Horas Extras (M,J) | E7: Horas Extras (Sábado)
A8: Scrum Master | B8: Josué | C8: 2 | D8: 3 | E8: 3
A9: Ingeniero de Requisitos | B9: Mateo | C9: 2 | D9: 3 | E9: 3
A10: Ingeniero de Requisitos | B10: Damián | C10: 2 | D10: 3 | E10: 3
A12: Trabajo por Semana
A13: Rol | B13: Integrante | C13: Días Normales (L,M,V) | D13: Días Extras (M,J) | E13: Días Extras (Sábado) | F13: Horas Normales por Semana | G13: Horas Extras por Semana | H13: Total de Horas por Semana
A14: Scrum Master | B14: Josué | C14: 3 | D14: 2 | E14: 1 | F14: =C14*C8 -> 6 | G14: =D14*D8 + E14*E8 -> 9 | H14: =F14+G14 -> 15
A15: Ingeniero de Requisitos | B15: Mateo | C15: 3 | D15: 2 | E15: 1 | F15: =C15*C9 -> 6 | G15: =D15*D9 + E15*E9 -> 9 | H15: =F15+G15 -> 15
A16: Ingeniero de Requisitos | B16: Damián | C16: 3 | D16: 2 | E16: 1 | F16: =C16*C10 -> 6 | G16: =D16*D10 + E16*E10 -> 9 | H16: =F16+G16 -> 15
A18: Trabajo por Semestre
A19: Rol | B19: Integrante | C19: Semanas por semestre | D19: Horas Normales por Semestre | E19: Horas Extras por Semestre | F19: Total de Horas por Semestre
A20: Scrum Master | B20: Josué | C20: 16 | D20: =F14*C20 -> 96 | E20: =G14*C20 -> 144 | F20: =D20+E20 -> 240
A21: Ingeniero de Requisitos | B21: Mateo | C21: 16 | D21: =F15*C21 -> 96 | E21: =G15*C21 -> 144 | F21: =D21+E21 -> 240
A22: Ingeniero de Requisitos | B22: Damián | C22: 16 | D22: =F16*C22 -> 96 | E22: =G16*C22 -> 144 | F22: =D22+E22 -> 240
A23: Total de horas en el semestre | F23: =SUM(F20:F22) -> 720

Sheet Materiales y Gastos
A1: Equipo | B1: Valor estimado (USD) | C1: Vida útil (meses) | D1: Depreciación mensual | E1: Meses de uso | F1: Subtotal | H1: Concepto | I1: Valor
A2: Laptop Josué | B2: 1200 | C2: 36 | D2: =B2/C2 -> 33.333333 | E2: 4 | F2: =D2*E2 -> 133.33333 | H2: Depreciación mensual | I2: =SUM(D2:D4) -> 105.55556
A3: Laptop Mateo | B3: 1600 | C3: 36 | D3: =B3/C3 -> 44.444444 | E3: 4 | F3: =D3*E3 -> 177.77778 | H3: Depreciación semanal | I3: =I2/4 -> 26.388889
A4: Laptop Damián | B4: 1000 | C4: 36 | D4: =B4/C4 -> 27.777778 | E4: 4 | F4: =D4*E4 -> 111.11111 | H4: Depreciación diaria | I4: =I3/3 -> 8.7962963
A5: TOTAL DEPRECIACIÓN DE EQUIPOS | F5: =SUM(F2:F4) -> 422.22222 | H5: Depreciación por hora | I5: =I4/4 -> 2.1990741
A9: Servicio por persona | B9: Consumo diario | C9: Consumo semanal | D9: Consumo mensual | E9: Costo diario | F9: Costo semanal | G9: Costo mensual
A10: Electricidad (kWh) | B10: 6 | C10: =B10*6 -> 36 | D10: =C10*4 -> 144 | E10: 0.6 | F10: =E10*6 -> 3.6 | G10: =F10*4 -> 14.4
A11: Agua (m³) | B11: 0.06 | C11: =B11*6 -> 0.36 | D11: =C11*4 -> 1.44 | E11: 0.18 | F11: =E11*6 -> 1.08 | G11: =F11*4 -> 4.32
A12: Internet | B12: 0.13 | C12: =B12*6 -> 0.78 | D12: =C12*4.33 -> 3.3774 | E12: 0.75 | F12: =E12*6 -> 4.5 | G12: =E12*30 -> 22.5
A13: Alimentación | B13: 1 | C13: =B13*6 -> 6 | D13: =C13*4 -> 24 | E13: 2.5 | F13: =E13*6 -> 15 | G13: =F13*4 -> 60
A14: Telefonía | B14: 1 | C14: =B14*6 -> 6 | D14: =B14*30 -> 30 | E14: 0.5 | F14: =E14*6 -> 3 | G14: =E14*30 -> 15
A15: Subtotal por persona | E15: =SUM(E10:E14) -> 4.53 | F15: =SUM(F10:F14) -> 27.18 | G15: =SUM(G10:G14) -> 116.22
A17: Servicio por Equipo | B17: Consumo diario | C17: Consumo semanal | D17: Consumo mensual | E17: Costo diario | F17: Costo semanal | G17: Costo mensual
A18: Electricidad (kWh) | B18: =B10*3 -> 18 | C18: =B18*6 -> 108 | D18: =D10*3 -> 432 | E18: =E10*3 -> 1.8 | F18: =F10*3 -> 10.8 | G18: =G10*3 -> 43.2
A19: Agua (m³) | B19: =B11*3 -> 0.18 | C19: =B19*6 -> 1.08 | D19: =D11*3 -> 4.32 | E19: =E11*3 -> 0.54 | F19: =F11*3 -> 3.24 | G19: =G11*3 -> 12.96
A20: Internet | B20: =B12*3 -> 0.39 | C20: =B20*6 -> 2.34 | D20: =D12*3 -> 10.1322 | E20: =E12*3 -> 2.25 | F20: =F12*3 -> 13.5 | G20: =G12*3 -> 67.5
A21: Alimentación | B21: =B13*3 -> 3 | C21: =C13*3 -> 18 | D21: =D13*3 -> 72 | E21: =E13*3 -> 7.5 | F21: =F13*3 -> 45 | G21: =G13*3 -> 180
A22: Telefonía | B22: =B14*3 -> 3 | C22: =C14*3 -> 18 | D22: =D14*3 -> 90 | E22: =E14*3 -> 1.5 | F22: =F14*3 -> 9 | G22: =G14*3 -> 45
A23: Subtotal por equipo | E23: =SUM(E18:E22) -> 13.59 | F23: =SUM(F18:F22) -> 81.54 | G23: =SUM(G18:G22) -> 348.66
A25: Persona × hora | B25: Consumo × hora | C25: Costo × hora
A26: Electricidad (kWh) | B26: =B10/5 -> 1.2 | C26: =E10/5 -> 0.12
A27: Agua (m³) | B27: =B11/5 -> 0.012 | C27: =E11/5 -> 0.036
A28: Internet | B28: =B12/5 -> 0.026 | C28: =E12/5 -> 0.15
A29: Alimentación | B29: =B13/5 -> 0.2 | C29: =E13/5 -> 0.5
A30: Telefonía | B30: =B14/5 -> 0.2 | C30: =E14/5 -> 0.1
A31: Subtotal por persona × hora | C31: =SUM(C26:C30) -> 0.906

Sheet Planificación
A1: CALENDARIO DE ACTIVIDADES — PROYECTO GESTIÓN DE AFORO
A2: Proyecto Iron Body Gym G3 | 16 semanas | 06/04/2026 → 26/07/2026
A3: Fase | B3: Actividad / Entregable | C3: Responsable | D3: S1 | E3: S2 | F3: S3 | G3: S4 | H3: S5 | I3: S6 | J3: S7 | K3: S8 | L3: S9 | M3: S10 | N3: S11 | O3: S12 | P3: S13 | Q3: S14 | R3: S15 | S3: S16
C4: Fechas → | D4: 06-12 abr | E4: 13-19 abr | F4: 20-26 abr | G4: 27 abr-03 may | H4: 04-10 may | I4: 11-17 may | J4: 18-24 may | K4: 25-31 may | L4: 01-07 jun | M4: 08-14 jun | N4: 15-21 jun | O4: 22-28 jun | P4: 29 jun-05 jul | Q4: 06-12 jul | R4: 13-19 jul | S4: 20-26 jul
A5: Fase 1 | B5: Planificación de la Reunión Entrevista | C5: Josué/Damián | J5: █
A6: Fase 1 | B6: Entrevsita al Gerente General | C6: Josué/Damian | K6: █
A7: Fase 1 | B7: Entrevsita al Entrenador | C7: Damián | K7: █
A8: Fase 1 | B8: Entrevista al Recepcionista | C8: Damián | K8: █
A9: Fase 1 | B9: Generación de la Minuta entrevista — Redacción | C9: Todos | K9: █
A10: Fase 1 | B10: Planificación de las preguntas de la encuesta en Google Forms | C10: Todos | J10: █
A11: Fase 1 | B11: Aplicación de encuesta a 45 usuarios de forma presencial | C11: Mateo | K11: █
A12: Fase 1 | B12: Generación de informe de la encuesta | C12: Mateo | K12: █
A13: Fase 2 | B13: Planificación de Árbol de Problemas | C13: Josué | L13: █ | M13: █
A14: Fase 2 | B14: Árbol de problemas: 4 causas y 4 consecuencias | C14: Josué | N14: █
A15: Fase 2 | B15: Planificación del Modelo Business Model Canvas | C15: Mateo/Damián | M15: █
A16: Fase 2 | B16: Business Model Canvas — Gestión de Aforo | C16: Todos | N16: █
A17: Fase 2 | B17: Diseño de la Solución | C17: Mateo | N17: █
A18: Fase 2 | B18: Propuesta de Solución 1 | C18: Todos | O18: █
A19: Fase 2 | B19: Desarrollo del Diagrama de casos de Uso de la primera Solución | C19: Todos | O19: █
A20: Fase 2 | B20: Propuesta de Solución 2 | C20: Josué | O20: █ | P20: █
A21: Fase 2 | B21: Desarrollo del Diagrama de casos de Uso de la segunda Solución | C21: Josué | O21: █ | P21: █
A22: Fase 3 | B22: Aprender a usar la herramienta ReqView | C22: Todos | N22: █ | O22: █ | P22: █ | Q22: █
A23: Fase 3 | B23: Redacción del Documento de Especificación de Requisitos de Software (ERS) | C23: Todos | Q23: █
A24: Fase 3 | B24: Validación y Revisión e Informe de Expertos | C24: Todos | Q24: █
A25: Fase 3 | B25: Corregir los requisitos segun las obsveraciones de los expertos | C25: Mateo/Damián | R25: █
A26: Fase 4 | B26: Elaboración y corrección de las interfaces | C26: Mateo/Damián | R26: █
A27: Fase 4 | B27: Elaboración y corrección de la base de datos | C27: Josué | R27: █
A28: Fase 4 | B28: Reunión de Validación Final con el cliente y promotor | C28: Todos | S28: █
A29: Fase 4 | B29: Estimación de costos por puntos de fución de la propuesta ganadora | C29: Josué | S29: █
A30: Fase 4 | B30: Ajustes Finales de la Línea Base de Requisitos | C30: Josué | S30: █

Sheet Costos
A1: RESUMEN DE COSTOS — PROYECTO GESTIÓN DE AFORO
A2: Fase | B2: Actividad / Entregable | C2: Responsable | D2: Horas Josué | E2: Horas Mateo | F2: Horas Damián | G2: Horas Totales | H2: Costo RH | I2: Costo Material | J2: Gastos Operativos | K2: Costo Total
A3: {='Planificación'!A5:C30} -> Fase 1 | B3: Planificación de la Reunión Entrevista | C3: Josué/Damián | D3: =IF(OR(ISNUMBER(SEARCH("Josué", C3)), ISNUMBER(SEARCH("Todos", C3))), 2, 0) -> 2 | E3: =IF(OR(ISNUMBER(SEARCH("Mateo", C3)), ISNUMBER(SEARCH("Todos", C3))), 2, 0) -> 0 | F3: =IF(OR(ISNUMBER(SEARCH("Damián", C3)), ISNUMBER(SEARCH("Todos", C3))), 2, 0) -> 2 | G3: =D3+E3+F3 -> 4 | H3: =D3*'Recursos Humanos'!$G$2 + E3*'Recursos Humanos'!$G$3 + F3*'Recursos Humanos'!$G$4 -> 63 | I3: =G3*'Materiales y Gastos'!$I$5 -> 8.7962963 | J3: =G3*'Materiales y Gastos'!$C$31 -> 3.624 | K3: =H3+I3+J3 -> 75.420296
A4: Fase 1 | B4: Entrevsita al Gerente General | C4: Josué/Damian | D4: =IF(OR(ISNUMBER(SEARCH("Josué", C4)), ISNUMBER(SEARCH("Todos", C4))), 2, 0) -> 2 | E4: =IF(OR(ISNUMBER(SEARCH("Mateo", C4)), ISNUMBER(SEARCH("Todos", C4))), 2, 0) -> 0 | F4: 2 | G4: =D4+E4+F4 -> 4 | H4: =D4*'Recursos Humanos'!$G$2 + E4*'Recursos Humanos'!$G$3 + F4*'Recursos Humanos'!$G$4 -> 63 | I4: =G4*'Materiales y Gastos'!$I$5 -> 8.7962963 | J4: =G4*'Materiales y Gastos'!$C$31 -> 3.624 | K4: =H4+I4+J4 -> 75.420296
A5: Fase 1 | B5: Entrevsita al Entrenador | C5: Damián | D5: =IF(OR(ISNUMBER(SEARCH("Josué", C5)), ISNUMBER(SEARCH("Todos", C5))), 2, 0) -> 0 | E5: =IF(OR(ISNUMBER(SEARCH("Mateo", C5)), ISNUMBER(SEARCH("Todos", C5))), 2, 0) -> 0 | F5: =IF(OR(ISNUMBER(SEARCH("Damián", C5)), ISNUMBER(SEARCH("Todos", C5))), 2, 0) -> 2 | G5: =D5+E5+F5 -> 2 | H5: =D5*'Recursos Humanos'!$G$2 + E5*'Recursos Humanos'!$G$3 + F5*'Recursos Humanos'!$G$4 -> 28 | I5: =G5*'Materiales y Gastos'!$I$5 -> 4.3981481 | J5: =G5*'Materiales y Gastos'!$C$31 -> 1.812 | K5: =H5+I5+J5 -> 34.210148
A6: Fase 1 | B6: Entrevista al Recepcionista | C6: Damián | D6: =IF(OR(ISNUMBER(SEARCH("Josué", C6)), ISNUMBER(SEARCH("Todos", C6))), 2, 0) -> 0 | E6: =IF(OR(ISNUMBER(SEARCH("Mateo", C6)), ISNUMBER(SEARCH("Todos", C6))), 2, 0) -> 0 | F6: =IF(OR(ISNUMBER(SEARCH("Damián", C6)), ISNUMBER(SEARCH("Todos", C6))), 2, 0) -> 2 | G6: =D6+E6+F6 -> 2 | H6: =D6*'Recursos Humanos'!$G$2 + E6*'Recursos Humanos'!$G$3 + F6*'Recursos Humanos'!$G$4 -> 28 | I6: =G6*'Materiales y Gastos'!$I$5 -> 4.3981481 | J6: =G6*'Materiales y Gastos'!$C$31 -> 1.812 | K6: =H6+I6+J6 -> 34.210148
A7: Fase 1 | B7: Generación de la Minuta entrevista — Redacción | C7: Todos | D7: =IF(OR(ISNUMBER(SEARCH("Josué", C7)), ISNUMBER(SEARCH("Todos", C7))), 2, 0) -> 2 | E7: =IF(OR(ISNUMBER(SEARCH("Mateo", C7)), ISNUMBER(SEARCH("Todos", C7))), 2, 0) -> 2 | F7: =IF(OR(ISNUMBER(SEARCH("Damián", C7)), ISNUMBER(SEARCH("Todos", C7))), 2, 0) -> 2 | G7: =D7+E7+F7 -> 6 | H7: =D7*'Recursos Humanos'!$G$2 + E7*'Recursos Humanos'!$G$3 + F7*'Recursos Humanos'!$G$4 -> 91 | I7: =G7*'Materiales y Gastos'!$I$5 -> 13.194444 | J7: =G7*'Materiales y Gastos'!$C$31 -> 5.436 | K7: =H7+I7+J7 -> 109.63044
A8: Fase 1 | B8: Planificación de las preguntas de la encuesta en Google Forms | C8: Todos | D8: =IF(OR(ISNUMBER(SEARCH("Josué", C8)), ISNUMBER(SEARCH("Todos", C8))), 2, 0) -> 2 | E8: 3 | F8: 3 | G8: =D8+E8+F8 -> 8 | H8: =D8*'Recursos Humanos'!$G$2 + E8*'Recursos Humanos'!$G$3 + F8*'Recursos Humanos'!$G$4 -> 119 | I8: =G8*'Materiales y Gastos'!$I$5 -> 17.592593 | J8: =G8*'Materiales y Gastos'!$C$31 -> 7.248 | K8: =H8+I8+J8 -> 143.84059
A9: Fase 1 | B9: Aplicación de encuesta a 45 usuarios de forma presencial | C9: Mateo | D9: =IF(OR(ISNUMBER(SEARCH("Josué", C9)), ISNUMBER(SEARCH("Todos", C9))), 2, 0) -> 0 | E9: 3 | F9: =IF(OR(ISNUMBER(SEARCH("Damián", C9)), ISNUMBER(SEARCH("Todos", C9))), 2, 0) -> 0 | G9: =D9+E9+F9 -> 3 | H9: =D9*'Recursos Humanos'!$G$2 + E9*'Recursos Humanos'!$G$3 + F9*'Recursos Humanos'!$G$4 -> 42 | I9: =G9*'Materiales y Gastos'!$I$5 -> 6.5972222 | J9: =G9*'Materiales y Gastos'!$C$31 -> 2.718 | K9: =H9+I9+J9 -> 51.315222
A10: Fase 1 | B10: Generación de informe de la encuesta | C10: Mateo | D10: =IF(OR(ISNUMBER(SEARCH("Josué", C10)), ISNUMBER(SEARCH("Todos", C10))), 2, 0) -> 0 | E10: 5 | F10: =IF(OR(ISNUMBER(SEARCH("Damián", C10)), ISNUMBER(SEARCH("Todos", C10))), 2, 0) -> 0 | G10: =D10+E10+F10 -> 5 | H10: =D10*'Recursos Humanos'!$G$2 + E10*'Recursos Humanos'!$G$3 + F10*'Recursos Humanos'!$G$4 -> 70 | I10: =G10*'Materiales y Gastos'!$I$5 -> 10.99537 | J10: =G10*'Materiales y Gastos'!$C$31 -> 4.53 | K10: =H10+I10+J10 -> 85.52537
A11: Fase 2 | B11: Planificación de Árbol de Problemas | C11: Josué | D11: 3 | E11: =IF(OR(ISNUMBER(SEARCH("Mateo", C11)), ISNUMBER(SEARCH("Todos", C11))), 2, 0) -> 0 | F11: =IF(OR(ISNUMBER(SEARCH("Damián", C11)), ISNUMBER(SEARCH("Todos", C11))), 2, 0) -> 0 | G11: =D11+E11+F11 -> 3 | H11: =D11*'Recursos Humanos'!$G$2 + E11*'Recursos Humanos'!$G$3 + F11*'Recursos Humanos'!$G$4 -> 52.5 | I11: =G11*'Materiales y Gastos'!$I$5 -> 6.5972222 | J11: =G11*'Materiales y Gastos'!$C$31 -> 2.718 | K11: =H11+I11+J11 -> 61.815222
A12: Fase 2 | B12: Árbol de problemas: 4 causas y 4 consecuencias | C12: Josué | D12: 5 | E12: =IF(OR(ISNUMBER(SEARCH("Mateo", C12)), ISNUMBER(SEARCH("Todos", C12))), 2, 0) -> 0 | F12: =IF(OR(ISNUMBER(SEARCH("Damián", C12)), ISNUMBER(SEARCH("Todos", C12))), 2, 0) -> 0 | G12: =D12+E12+F12 -> 5 | H12: =D12*'Recursos Humanos'!$G$2 + E12*'Recursos Humanos'!$G$3 + F12*'Recursos Humanos'!$G$4 -> 87.5 | I12: =G12*'Materiales y Gastos'!$I$5 -> 10.99537 | J12: =G12*'Materiales y Gastos'!$C$31 -> 4.53 | K12: =H12+I12+J12 -> 103.02537
A13: Fase 2 | B13: Planificación del Modelo Business Model Canvas | C13: Mateo/Damián | D13: =IF(OR(ISNUMBER(SEARCH("Josué", C13)), ISNUMBER(SEARCH("Todos", C13))), 2, 0) -> 0 | E13: =IF(OR(ISNUMBER(SEARCH("Mateo", C13)), ISNUMBER(SEARCH("Todos", C13))), 2, 0) -> 2 | F13: =IF(OR(ISNUMBER(SEARCH("Damián", C13)), ISNUMBER(SEARCH("Todos", C13))), 2, 0) -> 2 | G13: =D13+E13+F13 -> 4 | H13: =D13*'Recursos Humanos'!$G$2 + E13*'Recursos Humanos'!$G$3 + F13*'Recursos Humanos'!$G$4 -> 56 | I13: =G13*'Materiales y Gastos'!$I$5 -> 8.7962963 | J13: =G13*'Materiales y Gastos'!$C$31 -> 3.624 | K13: =H13+I13+J13 -> 68.420296
A14: Fase 2 | B14: Business Model Canvas — Gestión de Aforo | C14: Todos | D14: 3 | E14: 3 | F14: 1 | G14: =D14+E14+F14 -> 7 | H14: =D14*'Recursos Humanos'!$G$2 + E14*'Recursos Humanos'!$G$3 + F14*'Recursos Humanos'!$G$4 -> 108.5 | I14: =G14*'Materiales y Gastos'!$I$5 -> 15.393519 | J14: =G14*'Materiales y Gastos'!$C$31 -> 6.342 | K14: =H14+I14+J14 -> 130.23552
A15: Fase 2 | B15: Diseño de la Solución | C15: Mateo | D15: =IF(OR(ISNUMBER(SEARCH("Josué", C15)), ISNUMBER(SEARCH("Todos", C15))), 2, 0) -> 0 | E15: =IF(OR(ISNUMBER(SEARCH("Mateo", C15)), ISNUMBER(SEARCH("Todos", C15))), 2, 0) -> 2 | F15: =IF(OR(ISNUMBER(SEARCH("Damián", C15)), ISNUMBER(SEARCH("Todos", C15))), 2, 0) -> 0 | G15: =D15+E15+F15 -> 2 | H15: =D15*'Recursos Humanos'!$G$2 + E15*'Recursos Humanos'!$G$3 + F15*'Recursos Humanos'!$G$4 -> 28 | I15: =G15*'Materiales y Gastos'!$I$5 -> 4.3981481 | J15: =G15*'Materiales y Gastos'!$C$31 -> 1.812 | K15: =H15+I15+J15 -> 34.210148
A16: Fase 2 | B16: Propuesta de Solución 1 | C16: Todos | D16: =IF(OR(ISNUMBER(SEARCH("Josué", C16)), ISNUMBER(SEARCH("Todos", C16))), 2, 0) -> 2 | E16: =IF(OR(ISNUMBER(SEARCH("Mateo", C16)), ISNUMBER(SEARCH("Todos", C16))), 2, 0) -> 2 | F16: =IF(OR(ISNUMBER(SEARCH("Damián", C16)), ISNUMBER(SEARCH("Todos", C16))), 2, 0) -> 2 | G16: =D16+E16+F16 -> 6 | H16: =D16*'Recursos Humanos'!$G$2 + E16*'Recursos Humanos'!$G$3 + F16*'Recursos Humanos'!$G$4 -> 91 | I16: =G16*'Materiales y Gastos'!$I$5 -> 13.194444 | J16: =G16*'Materiales y Gastos'!$C$31 -> 5.436 | K16: =H16+I16+J16 -> 109.63044
A17: Fase 2 | B17: Desarrollo del Diagrama de casos de Uso de la primera Solución | C17: Todos | D17: 4 | E17: 4 | F17: 4 | G17: =D17+E17+F17 -> 12 | H17: =D17*'Recursos Humanos'!$G$2 + E17*'Recursos Humanos'!$G$3 + F17*'Recursos Humanos'!$G$4 -> 182 | I17: =G17*'Materiales y Gastos'!$I$5 -> 26.388889 | J17: =G17*'Materiales y Gastos'!$C$31 -> 10.872 | K17: =H17+I17+J17 -> 219.26089
A18: Fase 2 | B18: Propuesta de Solución 2 | C18: Josué | D18: 5 | E18: =IF(OR(ISNUMBER(SEARCH("Mateo", C18)), ISNUMBER(SEARCH("Todos", C18))), 2, 0) -> 0 | F18: =IF(OR(ISNUMBER(SEARCH("Damián", C18)), ISNUMBER(SEARCH("Todos", C18))), 2, 0) -> 0 | G18: =D18+E18+F18 -> 5 | H18: =D18*'Recursos Humanos'!$G$2 + E18*'Recursos Humanos'!$G$3 + F18*'Recursos Humanos'!$G$4 -> 87.5 | I18: =G18*'Materiales y Gastos'!$I$5 -> 10.99537 | J18: =G18*'Materiales y Gastos'!$C$31 -> 4.53 | K18: =H18+I18+J18 -> 103.02537
A19: Fase 2 | B19: Desarrollo del Diagrama de casos de Uso de la segunda Solución | C19: Josué | D19: 3 | E19: =IF(OR(ISNUMBER(SEARCH("Mateo", C19)), ISNUMBER(SEARCH("Todos", C19))), 2, 0) -> 0 | F19: =IF(OR(ISNUMBER(SEARCH("Damián", C19)), ISNUMBER(SEARCH("Todos", C19))), 2, 0) -> 0 | G19: =D19+E19+F19 -> 3 | H19: =D19*'Recursos Humanos'!$G$2 + E19*'Recursos Humanos'!$G$3 + F19*'Recursos Humanos'!$G$4 -> 52.5 | I19: =G19*'Materiales y Gastos'!$I$5 -> 6.5972222 | J19: =G19*'Materiales y Gastos'!$C$31 -> 2.718 | K19: =H19+I19+J19 -> 61.815222
A20: Fase 3 | B20: Aprender a usar la herramienta ReqView | C20: Todos | D20: 4 | E20: 4 | F20: 4 | G20: =D20+E20+F20 -> 12 | H20: =D20*'Recursos Humanos'!$G$2 + E20*'Recursos Humanos'!$G$3 + F20*'Recursos Humanos'!$G$4 -> 182 | I20: =G20*'Materiales y Gastos'!$I$5 -> 26.388889 | J20: =G20*'Materiales y Gastos'!$C$31 -> 10.872 | K20: =H20+I20+J20 -> 219.26089
A21: Fase 3 | B21: Redacción del Documento de Especificación de Requisitos de Software (ERS) | C21: Todos | D21: 6 | E21: =IF(OR(ISNUMBER(SEARCH("Mateo", C21)), ISNUMBER(SEARCH("Todos", C21))), 2, 0) -> 2 | F21: =IF(OR(ISNUMBER(SEARCH("Damián", C21)), ISNUMBER(SEARCH("Todos", C21))), 2, 0) -> 2 | G21: =D21+E21+F21 -> 10 | H21: =D21*'Recursos Humanos'!$G$2 + E21*'Recursos Humanos'!$G$3 + F21*'Recursos Humanos'!$G$4 -> 161 | I21: =G21*'Materiales y Gastos'!$I$5 -> 21.990741 | J21: =G21*'Materiales y Gastos'!$C$31 -> 9.06 | K21: =H21+I21+J21 -> 192.05074
A22: Fase 3 | B22: Validación y Revisión e Informe de Expertos | C22: Todos | D22: 1 | E22: =IF(OR(ISNUMBER(SEARCH("Mateo", C22)), ISNUMBER(SEARCH("Todos", C22))), 2, 0) -> 2 | F22: =IF(OR(ISNUMBER(SEARCH("Damián", C22)), ISNUMBER(SEARCH("Todos", C22))), 2, 0) -> 2 | G22: =D22+E22+F22 -> 5 | H22: =D22*'Recursos Humanos'!$G$2 + E22*'Recursos Humanos'!$G$3 + F22*'Recursos Humanos'!$G$4 -> 73.5 | I22: =G22*'Materiales y Gastos'!$I$5 -> 10.99537 | J22: =G22*'Materiales y Gastos'!$C$31 -> 4.53 | K22: =H22+I22+J22 -> 89.02537
A23: Fase 3 | B23: Corregir los requisitos segun las obsveraciones de los expertos | C23: Mateo/Damián | D23: =IF(OR(ISNUMBER(SEARCH("Josué", C23)), ISNUMBER(SEARCH("Todos", C23))), 2, 0) -> 0 | E23: =IF(OR(ISNUMBER(SEARCH("Mateo", C23)), ISNUMBER(SEARCH("Todos", C23))), 2, 0) -> 2 | F23: =IF(OR(ISNUMBER(SEARCH("Damián", C23)), ISNUMBER(SEARCH("Todos", C23))), 2, 0) -> 2 | G23: =D23+E23+F23 -> 4 | H23: =D23*'Recursos Humanos'!$G$2 + E23*'Recursos Humanos'!$G$3 + F23*'Recursos Humanos'!$G$4 -> 56 | I23: =G23*'Materiales y Gastos'!$I$5 -> 8.7962963 | J23: =G23*'Materiales y Gastos'!$C$31 -> 3.624 | K23: =H23+I23+J23 -> 68.420296
A24: Fase 4 | B24: Elaboración y corrección de las interfaces | C24: Mateo/Damián | D24: =IF(OR(ISNUMBER(SEARCH("Josué", C24)), ISNUMBER(SEARCH("Todos", C24))), 2, 0) -> 0 | E24: 4 | F24: 4 | G24: =D24+E24+F24 -> 8 | H24: =D24*'Recursos Humanos'!$G$2 + E24*'Recursos Humanos'!$G$3 + F24*'Recursos Humanos'!$G$4 -> 112 | I24: =G24*'Materiales y Gastos'!$I$5 -> 17.592593 | J24: =G24*'Materiales y Gastos'!$C$31 -> 7.248 | K24: =H24+I24+J24 -> 136.84059
A25: Fase 4 | B25: Elaboración y corrección de la base de datos | C25: Josué | D25: 3 | E25: =IF(OR(ISNUMBER(SEARCH("Mateo", C25)), ISNUMBER(SEARCH("Todos", C25))), 2, 0) -> 0 | F25: =IF(OR(ISNUMBER(SEARCH("Damián", C25)), ISNUMBER(SEARCH("Todos", C25))), 2, 0) -> 0 | G25: =D25+E25+F25 -> 3 | H25: =D25*'Recursos Humanos'!$G$2 + E25*'Recursos Humanos'!$G$3 + F25*'Recursos Humanos'!$G$4 -> 52.5 | I25: =G25*'Materiales y Gastos'!$I$5 -> 6.5972222 | J25: =G25*'Materiales y Gastos'!$C$31 -> 2.718 | K25: =H25+I25+J25 -> 61.815222
A26: Fase 4 | B26: Reunión de Validación Final con el cliente y promotor | C26: Todos | D26: 1 | E26: 1 | F26: 1 | G26: =D26+E26+F26 -> 3 | H26: =D26*'Recursos Humanos'!$G$2 + E26*'Recursos Humanos'!$G$3 + F26*'Recursos Humanos'!$G$4 -> 45.5 | I26: =G26*'Materiales y Gastos'!$I$5 -> 6.5972222 | J26: =G26*'Materiales y Gastos'!$C$31 -> 2.718 | K26: =H26+I26+J26 -> 54.815222
A27: Fase 4 | B27: Estimación de costos por puntos de fución de la propuesta ganadora | C27: Josué | D27: 3 | E27: =IF(OR(ISNUMBER(SEARCH("Mateo", C27)), ISNUMBER(SEARCH("Todos", C27))), 2, 0) -> 0 | F27: =IF(OR(ISNUMBER(SEARCH("Damián", C27)), ISNUMBER(SEARCH("Todos", C27))), 2, 0) -> 0 | G27: =D27+E27+F27 -> 3 | H27: =D27*'Recursos Humanos'!$G$2 + E27*'Recursos Humanos'!$G$3 + F27*'Recursos Humanos'!$G$4 -> 52.5 | I27: =G27*'Materiales y Gastos'!$I$5 -> 6.5972222 | J27: =G27*'Materiales y Gastos'!$C$31 -> 2.718 | K27: =H27+I27+J27 -> 61.815222
A28: Fase 4 | B28: Ajustes Finales de la Línea Base de Requisitos | C28: Josué | D28: 4 | E28: =IF(OR(ISNUMBER(SEARCH("Mateo", C28)), ISNUMBER(SEARCH("Todos", C28))), 2, 0) -> 0 | F28: =IF(OR(ISNUMBER(SEARCH("Damián", C28)), ISNUMBER(SEARCH("Todos", C28))), 2, 0) -> 0 | G28: =D28+E28+F28 -> 4 | H28: =D28*'Recursos Humanos'!$G$2 + E28*'Recursos Humanos'!$G$3 + F28*'Recursos Humanos'!$G$4 -> 70 | I28: =G28*'Materiales y Gastos'!$I$5 -> 8.7962963 | J28: =G28*'Materiales y Gastos'!$C$31 -> 3.624 | K28: =H28+I28+J28 -> 82.420296
A29: Total General | K29: =SUM(K3:K28) -> 2467.4749

Sheet Resumen
A1: Concepto | B1: Monto
A2: Fase 1 | B2: =SUMIF(Costos!A:A, "Fase 1", Costos!K:K) -> 609.57252
A3: Fase 2 | B3: =SUMIF(Costos!A:A, "Fase 2", Costos!K:K) -> 891.43848
A4: Fase 3 | B4: =SUMIF(Costos!A:A, "Fase 3", Costos!K:K) -> 568.7573
A5: Fase 4 | B5: =SUMIF(Costos!A:A, "Fase 4", Costos!K:K) -> 397.70656
A6: sub Total | B6: =SUM(B2:B5) -> 2467.4749
A7: Contingencia a los riesgos (10 %) | B7: =MULTIPLY(B6, 0.1) -> 246.74749
A8: Total del 20% del proyecto | B8: =SUM(B6,B7) -> 2714.2223
A9: Total proyecto 100% | B9: =B8/0.2 -> 13571.112
